tiidan_utils/__init__.py
tiidan_utils/__main__.py
tiidan_utils/aws_utils.py
tiidan_utils/cli.py
tiidan_utils/crypto.py
tiidan_utils/logger.py
tiidan_utils/sql_handler.py
tiidan_utils/util.py
tiidan_utils/cli/__init__.py
tiidan_utils/cli/main.py
tiidan_utils/lambda_argument_parser/__init__.py
tiidan_utils/lambda_argument_parser/main.py
tiidan_utils/quota_manager/__init__.py
tiidan_utils/quota_manager/quota_manager.py
tiidan_utils/quota_manager/models/__init__.py
tiidan_utils/quota_manager/models/api_key.py
tiidan_utils/quota_manager/models/base.py
tiidan_utils/quota_manager/models/quota.py
tiidan_utils/quota_manager/models/usage.py
tiidan_utils/quota_manager/scripts/__init__.py
tiidan_utils/quota_manager/scripts/add_quota.py
tiidan_utils/quota_manager/scripts/create_tables.py
tiidan_utils/quota_manager/scripts/main.py
tiidan_utils/quota_manager/scripts/new_key.py
tiidan_utils/quota_manager/scripts/url.py
tiidan_utils-0.0.2.dist-info/AUTHORS.rst
tiidan_utils-0.0.2.dist-info/LICENSE
tiidan_utils-0.0.2.dist-info/METADATA
tiidan_utils-0.0.2.dist-info/WHEEL
tiidan_utils-0.0.2.dist-info/entry_points.txt
tiidan_utils-0.0.2.dist-info/top_level.txt
tiidan_utils-0.0.2.dist-info/RECORD
