Metadata-Version: 2.1
Name: tiidan-utils
Version: 0.0.2
Summary: Tiidan utils in python.
Home-page: https://bitbucket.org/tiidan/python-utils
Author: Imri Paran
Author-email: imri@tiidan.com
License: BSD 2-Clause License
Project-URL: Documentation, https://python-tiidan-utils.readthedocs.io/
Project-URL: Changelog, https://python-tiidan-utils.readthedocs.io/en/latest/changelog.html
Project-URL: Issue Tracker, https://github.com/ionelmc/python-tiidan-utils/issues
Platform: UNKNOWN
Classifier: Development Status :: 5 - Production/Stable
Classifier: Intended Audience :: Developers
Classifier: License :: OSI Approved :: BSD License
Classifier: Operating System :: Unix
Classifier: Operating System :: POSIX
Classifier: Operating System :: Microsoft :: Windows
Classifier: Programming Language :: Python
Classifier: Programming Language :: Python :: 2.7
Classifier: Programming Language :: Python :: 3
Classifier: Programming Language :: Python :: 3.4
Classifier: Programming Language :: Python :: 3.5
Classifier: Programming Language :: Python :: 3.6
Classifier: Programming Language :: Python :: 3.7
Classifier: Programming Language :: Python :: Implementation :: CPython
Classifier: Programming Language :: Python :: Implementation :: PyPy
Classifier: Topic :: Utilities
Requires-Python: >=2.7, !=3.0.*, !=3.1.*, !=3.2.*, !=3.3.*
Requires-Dist: click
Requires-Dist: ssm-parameter-store (==19.5.0)
Requires-Dist: botocore
Requires-Dist: boto3
Requires-Dist: numpy
Requires-Dist: sqlalchemy
Requires-Dist: pandas
